ddpaper/__init__.py
ddpaper/data.py
ddpaper/draftdata.py
ddpaper/filters.py
ddpaper/generate.py
ddpaper/render.py
ddpaper/yaml.py
linked_data_latex-0.1.5.dist-info/METADATA
linked_data_latex-0.1.5.dist-info/WHEEL
linked_data_latex-0.1.5.dist-info/entry_points.txt
linked_data_latex-0.1.5.dist-info/RECORD
